_nod.cp312-win_amd64.pyd
fmt.lib
logvisor.lib
nod.lib
nod/__init__.py
nod/__main__.py
nod/types.py
nod/version.py
nod-1.9.5.dist-info/licenses/LICENSE
nod-1.9.5.dist-info/METADATA
nod-1.9.5.dist-info/WHEEL
nod-1.9.5.dist-info/top_level.txt
nod-1.9.5.dist-info/RECORD
